super_nest/__init__.py
super_nest/super_nest.py
super_nest-1.0.0.dist-info/LICENSE
super_nest-1.0.0.dist-info/METADATA
super_nest-1.0.0.dist-info/WHEEL
super_nest-1.0.0.dist-info/top_level.txt
super_nest-1.0.0.dist-info/RECORD
