Metadata-Version: 2.1
Name: super-nest
Version: 1.0.0
Summary: A wrapper for use of SSPR in nested sampling packages such as PolyChord and Multinest
Home-page: https://gitlab.com/a-p-petrosyan/sspr
Author: Aleksandr Petrosyan
Author-email: a-p-petrosyan@yandex.ru
License: MIT
Platform: UNKNOWN
Requires-Python: >=3.6
Requires-Dist: anesthetic
Requires-Dist: pypolychord
Requires-Dist: numpy
Requires-Dist: matplotlib
